b_cfn_lambda_layer/Dockerfile
b_cfn_lambda_layer/__init__.py
b_cfn_lambda_layer/dependency.py
b_cfn_lambda_layer/lambda_layer.py
b_cfn_lambda_layer/lambda_layer_code.py
b_cfn_lambda_layer/package_version.py
b_cfn_lambda_layer/pip_install.py
b_cfn_lambda_layer/dockerignore/.dockerignore
b_cfn_lambda_layer/tmp/__init__.py
b_cfn_lambda_layer/tmp/layer1/layer1/__init__.py
b_cfn_lambda_layer/tmp/layer1/layer1/dummy_module.py
b_cfn_lambda_layer/tmp/layer2/layer2/__init__.py
b_cfn_lambda_layer/tmp/layer2/layer2/dummy_module.py
b_cfn_lambda_layer/tmp/layer3/layer3/__init__.py
b_cfn_lambda_layer/tmp/layer3/layer3/dummy_module.py
b_cfn_lambda_layer/tmp/layer_cross_stack/layer_cross_stack/__init__.py
b_cfn_lambda_layer/tmp/layer_cross_stack/layer_cross_stack/dummy_module.py
b_cfn_lambda_layer/tmp/layer_source/layer_source/__init__.py
b_cfn_lambda_layer/tmp/layer_source/layer_source/dummy_module.py
b_cfn_lambda_layer_test/integration/__init__.py
b_cfn_lambda_layer_test/integration/app.py
b_cfn_lambda_layer_test/integration/conftest.py
b_cfn_lambda_layer_test/integration/infrastructure/__init__.py
b_cfn_lambda_layer_test/integration/infrastructure/cross_stack_layers.py
b_cfn_lambda_layer_test/integration/infrastructure/function1.py
b_cfn_lambda_layer_test/integration/infrastructure/function2.py
b_cfn_lambda_layer_test/integration/infrastructure/function3.py
b_cfn_lambda_layer_test/integration/infrastructure/function4.py
b_cfn_lambda_layer_test/integration/infrastructure/main_stack.py
b_cfn_lambda_layer_test/integration/infrastructure/layer1/__init__.py
b_cfn_lambda_layer_test/integration/infrastructure/layer1/dummy_module.py
b_cfn_lambda_layer_test/integration/infrastructure/layer2/__init__.py
b_cfn_lambda_layer_test/integration/infrastructure/layer2/dummy_module.py
b_cfn_lambda_layer_test/integration/infrastructure/layer3/__init__.py
b_cfn_lambda_layer_test/integration/infrastructure/layer3/dummy_module.py
b_cfn_lambda_layer-3.0.0.dist-info/LICENSE
b_cfn_lambda_layer-3.0.0.dist-info/METADATA
b_cfn_lambda_layer-3.0.0.dist-info/WHEEL
b_cfn_lambda_layer-3.0.0.dist-info/top_level.txt
b_cfn_lambda_layer-3.0.0.dist-info/RECORD
