Metadata-Version: 2.1
Name: b-cfn-lambda-layer
Version: 3.0.0
Summary: AWS CDK based lambda layer including useful utilities.
Home-page: https://github.com/biomapas/B.CfnLambdaLayer.git
Author: Laimonas Sutkus
Author-email: laimonas.sutkus@biomapas.com
License: Apache License 2.0
Keywords: AWS CDK Lambda Layer
Classifier: Programming Language :: Python :: 3
Classifier: Operating System :: OS Independent
License-File: LICENSE
Requires-Dist: aws-cdk-lib (<3.0.0,>=2.0.0)
Requires-Dist: aws-cdk-constructs (<3.0.0,>=2.0.0)
